pipecashagents/ExampleAgent.py
pipecashagents/__init__.py
pipecashagents/DataFormats/RSS.py
pipecashagents/DataFormats/__init__.py
pipecashagents/Email/Email.py
pipecashagents/Email/__init__.py
pipecashagents/EventGates/DifferenceDetection.py
pipecashagents/EventGates/EventTimingAgents.py
pipecashagents/EventGates/Lists.py
pipecashagents/EventGates/RegexFilter.py
pipecashagents/EventGates/__init__.py
pipecashagents/Exchanges/__init__.py
pipecashagents/HandCash/GetHandCashAddress.py
pipecashagents/HandCash/__init__.py
pipecashagents/MetaNet/OpReturn.py
pipecashagents/MetaNet/__init__.py
pipecashagents/OS/ReadFile.py
pipecashagents/OS/ShellCommand.py
pipecashagents/OS/WatchDir.py
pipecashagents/OS/Write.py
pipecashagents/OS/__init__.py
pipecashagents/Twitter/__init__.py
pipecashagents/Twitter/twitterAgents.py
pipecashagents/WalletAgents/WalletAgents.py
pipecashagents/WalletAgents/__init__.py
pipecashagents/Web/ScrapeHTML.py
pipecashagents/Web/__init__.py
pipecashagents-0.1.2.8.dist-info/AUTHORS.rst
pipecashagents-0.1.2.8.dist-info/LICENSE
pipecashagents-0.1.2.8.dist-info/METADATA
pipecashagents-0.1.2.8.dist-info/WHEEL
pipecashagents-0.1.2.8.dist-info/top_level.txt
pipecashagents-0.1.2.8.dist-info/RECORD
