Metadata-Version: 2.1
Name: pipecashagents
Version: 0.1.2.8
Summary: A collection of common agents used in PipeCash. Learn more about PipeCash on http://pipe.cash/
Home-page: https://github.com/Pipe-Cash/pipecashagents
Author: Aleksandar Nikolaev Dinkov
Author-email: alexander.n.dinkov@gmail.com
License: MIT license
Keywords: pipecashagents
Platform: UNKNOWN
Classifier: Development Status :: 2 - Pre-Alpha
Classifier: Intended Audience :: Developers
Classifier: Natural Language :: English
Classifier: Programming Language :: Python :: 3
Classifier: Programming Language :: Python :: 3.4
Classifier: Programming Language :: Python :: 3.5
Classifier: Programming Language :: Python :: 3.6
Classifier: Programming Language :: Python :: 3.7
